example_usage.py
netconf_xml_builder/__init__.py
netconf_xml_builder/netconf_xml_builder.py
netconf_xml_builder-0.1.0.dist-info/licenses/LICENSE
netconf_xml_builder-0.1.0.dist-info/METADATA
netconf_xml_builder-0.1.0.dist-info/WHEEL
netconf_xml_builder-0.1.0.dist-info/top_level.txt
netconf_xml_builder-0.1.0.dist-info/RECORD
