Metadata-Version: 2.4
Name: netconf-xml-builder
Version: 0.1.0
Summary: Python library helping to create NETCONF XML messages
Author-email: Michal Novák <it.novakmi@gmail.com>
Maintainer-email: Michal Novák <it.novakmi@gmail.com>
License: MIT license
License-File: LICENSE
Provides-Extra: dev
Requires-Dist: coverage; extra == "dev"
Requires-Dist: mypy; extra == "dev"
Requires-Dist: pytest; extra == "dev"
Requires-Dist: ruff; extra == "dev"
Dynamic: license-file
